ashare_core/DailyReader.py
ashare_core/DayLineTxtReader.py
ashare_core/__init__.py
ashare_core/py.typed
ashare_core-0.2.0.dist-info/METADATA
ashare_core-0.2.0.dist-info/WHEEL
ashare_core-0.2.0.dist-info/RECORD
