Metadata-Version: 2.4
Name: ashare_core
Version: 0.2.0
Summary: Add your description here
Author-email: szzend <szzend@qq.com>
Requires-Python: >=3.12
Requires-Dist: openpyxl>=3.1.5
Requires-Dist: pandas>=2.2.3
